{
    "diagramm_settings": {
        "diagramm_type_id": 0,
        "diagramm_name": "Скелетная схема ВОЛП и основные данные цепей кабеля"
    },
    "image_settings": {
        "width": 2000,
        "height": 600,
        "start_x": 150,
        "start_y": 150
    },
    "nodes": [
        {
            "id": "c640ff886a6c4813b104e8f7fa040c9c",
            "order": 0,
            "node_id": "0",
            "data": {
                "название": {
                    "name": "Название",
                    "order": 0,
                    "value": "Маленький круг"
                }
            },
            "is_wrap": false,
            "metrics": {
                "margin_left_right": {
                    "is_global": false,
                    "name": "Боковые внешние отступы вершины",
                    "order": 0,
                    "value": 16
                },
                "margin_top": {
                    "is_global": false,
                    "name": "Высота названия над вершиной",
                    "order": 1,
                    "value": 32
                },
                "radius": {
                    "is_global": true,
                    "name": "Радиус круга",
                    "order": 4,
                    "value": 16
                },
                "title_pixel_size": {
                    "is_global": true,
                    "name": "Размер шрифта для названия",
                    "order": 2,
                    "value": 12
                }
            }
        },
        {
            "id": "1c918fe681e44fb19c9c21e3a9e82180",
            "order": 1,
            "node_id": "0",
            "data": {
                "название": {
                    "name": "Название",
                    "order": 0,
                    "value": "Маленький круг"
                }
            },
            "is_wrap": false,
            "metrics": {
                "margin_left_right": {
                    "is_global": false,
                    "name": "Боковые внешние отступы вершины",
                    "order": 0,
                    "value": 16
                },
                "margin_top": {
                    "is_global": false,
                    "name": "Высота названия над вершиной",
                    "order": 1,
                    "value": 32
                },
                "radius": {
                    "is_global": true,
                    "name": "Радиус круга",
                    "order": 4,
                    "value": 16
                },
                "title_pixel_size": {
                    "is_global": true,
                    "name": "Размер шрифта для названия",
                    "order": 2,
                    "value": 12
                }
            }
        },
        {
            "id": "603a8da6bbfb4fa6a751614c512ab0f3",
            "order": 2,
            "node_id": "0",
            "data": {
                "название": {
                    "name": "Название",
                    "order": 0,
                    "value": "Маленький круг"
                }
            },
            "is_wrap": false,
            "metrics": {
                "margin_left_right": {
                    "is_global": false,
                    "name": "Боковые внешние отступы вершины",
                    "order": 0,
                    "value": 16
                },
                "margin_top": {
                    "is_global": false,
                    "name": "Высота названия над вершиной",
                    "order": 1,
                    "value": 32
                },
                "radius": {
                    "is_global": true,
                    "name": "Радиус круга",
                    "order": 4,
                    "value": 16
                },
                "title_pixel_size": {
                    "is_global": true,
                    "name": "Размер шрифта для названия",
                    "order": 2,
                    "value": 12
                }
            }
        },
        {
            "id": "3fa1989e9bf0456fa76b62c634f2f458",
            "order": 3,
            "node_id": "0",
            "data": {
                "название": {
                    "name": "Название",
                    "order": 0,
                    "value": "Маленький круг"
                }
            },
            "is_wrap": false,
            "metrics": {
                "margin_left_right": {
                    "is_global": false,
                    "name": "Боковые внешние отступы вершины",
                    "order": 0,
                    "value": 16
                },
                "margin_top": {
                    "is_global": false,
                    "name": "Высота названия над вершиной",
                    "order": 1,
                    "value": 32
                },
                "radius": {
                    "is_global": true,
                    "name": "Радиус круга",
                    "order": 4,
                    "value": 16
                },
                "title_pixel_size": {
                    "is_global": true,
                    "name": "Размер шрифта для названия",
                    "order": 2,
                    "value": 12
                }
            }
        }
    ],
    "connections": [
        {
            "id": "a81a658408f34864a343f542ec202a30",
            "order": 0,
            "connection_id": "0",
            "data": {
                "ВОК": {
                    "value": "ВОК "
                },
                "количество_ОВ": {
                    "value": "кол-во ОВ - "
                },
                "местоположение": {
                    "value": "Местоположение (над линией)"
                },
                "местоположение_доп": {
                    "value": "выаыва"
                },
                "название": {
                    "value": "Синяя линия"
                },
                "название_доп": {
                    "value": "Синяя линиявааыа"
                },
                "оптическая_длина": {
                    "value": "оптическая_длина - "
                },
                "физическая_длина": {
                    "value": "физическая длина - \n"
                }
            },
            "metrics": {
                "delta_node_and_thin_line": {
                    "value": 80
                },
                "delta_thins_lines": {
                    "value": 45
                },
                "left_right_margin": {
                    "value": 10
                },
                "length": {
                    "value": 350
                },
                "main_label_vertical_padding": {
                    "value": 5
                },
                "thin_label_vertical_padding": {
                    "value": 8
                }
            }
        },
        {
            "id": "0468b41a0c0f487fb5665c3fd839e971",
            "order": 1,
            "connection_id": "0",
            "data": {
                "ВОК": {
                    "name": "ВОК",
                    "order": 2,
                    "value": "ВОК "
                },
                "количество_ОВ": {
                    "name": "Количество ОВ",
                    "order": 3,
                    "value": "кол-во ОВ - "
                },
                "местоположение": {
                    "name": "Местоположение",
                    "order": 6,
                    "value": "Местоположение (над линией)"
                },
                "местоположение_доп": {
                    "name": "Местоположение (под линией)",
                    "order": 7,
                    "value": ""
                },
                "название": {
                    "name": "Название (над линией)",
                    "order": 0,
                    "value": "Синяя линия"
                },
                "название_доп": {
                    "name": "Дополнительное название (под линией)",
                    "order": 1,
                    "value": "Синяя линия"
                },
                "оптическая_длина": {
                    "name": "Оптическая длина",
                    "order": 5,
                    "value": "оптическая_длина - "
                },
                "физическая_длина": {
                    "name": "Физическая длина",
                    "order": 4,
                    "value": "физическая длина - "
                }
            },
            "metrics": {
                "delta_node_and_thin_line": {
                    "value": 80
                },
                "delta_thins_lines": {
                    "value": 45
                },
                "left_right_margin": {
                    "is_global": false,
                    "name": "Боковые отступы подписей от вершин",
                    "order": 1,
                    "value": 10
                },
                "length": {
                    "is_global": false,
                    "name": "Длина соединения",
                    "order": 0,
                    "value": 350
                },
                "main_label_vertical_padding": {
                    "is_global": false,
                    "name": "Высота подписей над/под соединением",
                    "order": 2,
                    "value": 10
                },
                "thin_label_vertical_padding": {
                    "value": 8
                }
            }
        },
        {
            "id": "77dd16105d6943209a61014c5a212778",
            "order": 2,
            "connection_id": "0",
            "data": {
                "ВОК": {
                    "name": "ВОК",
                    "order": 2,
                    "value": "ВОК "
                },
                "количество_ОВ": {
                    "name": "Количество ОВ",
                    "order": 3,
                    "value": "кол-во ОВ - "
                },
                "местоположение": {
                    "name": "Местоположение",
                    "order": 6,
                    "value": "Местоположение (над линией)"
                },
                "местоположение_доп": {
                    "name": "Местоположение (под линией)",
                    "order": 7,
                    "value": ""
                },
                "название": {
                    "name": "Название (над линией)",
                    "order": 0,
                    "value": "Синяя линия"
                },
                "название_доп": {
                    "name": "Дополнительное название (под линией)",
                    "order": 1,
                    "value": "Синяя линия"
                },
                "оптическая_длина": {
                    "name": "Оптическая длина",
                    "order": 5,
                    "value": "оптическая_длина - "
                },
                "физическая_длина": {
                    "name": "Физическая длина",
                    "order": 4,
                    "value": "физическая длина - "
                }
            },
            "metrics": {
                "delta_node_and_thin_line": {
                    "value": 80
                },
                "delta_thins_lines": {
                    "value": 45
                },
                "left_right_margin": {
                    "is_global": false,
                    "name": "Боковые отступы подписей от вершин",
                    "order": 1,
                    "value": 10
                },
                "length": {
                    "is_global": false,
                    "name": "Длина соединения",
                    "order": 0,
                    "value": 350
                },
                "main_label_vertical_padding": {
                    "is_global": false,
                    "name": "Высота подписей над/под соединением",
                    "order": 2,
                    "value": 10
                },
                "thin_label_vertical_padding": {
                    "value": 8
                }
            }
        }
    ]
}