{
    "image_parameters": {
        "width": {
            "value": 2000,
            "name": "Ширина изображения",
            "order": 0
        },
        "height": {
            "value": 1000,
            "name": "Высота изображения",
            "order": 1
        }
    },
    "diagramms": {
        "0": {
            "order": 0,
            "type_id": "0",
            "name": "Скелетная схема ВОЛП и основные данные цепей кабеля",
            "id_nodes": [
                "0",
                "1"
            ],
            "id_connections": [
                "0"
            ],
            "parameters": {
                "start_x": {
                    "value": 150,
                    "name": "Стартовая координата X",
                    "order": 1
                },
                "start_y": {
                    "value": 100,
                    "name": "Стартовая координата Y",
                    "order": 2
                },
                "delta_wrap_y": {
                    "value": 300,
                    "name": "Расстояние между рядами вершин по Y",
                    "order": 3
                },
                "font_name": {
                    "value": "",
                    "name": "Название шрифта диграммы",
                    "order": 4,
                    "type": "font_name"
                },
                "is_location": {
                    "value": true,
                    "name": "Показывать местоположение",
                    "order": 5,
                    "type": "bool"
                },
                "Тонкие линии": {
                    "value": "",
                    "name": "Тонкие линии",
                    "order": 50,
                    "type": "title"
                },
                "thin_line_color": {
                    "value": "#000000",
                    "name": "Цвет тонкой линии",
                    "order": 51,
                    "type": "color"
                },
                "thin_line_weight": {
                    "value": 2,
                    "name": "Толщина тонкой линии",
                    "order": 52
                },
                "Расстояния": {
                    "value": "",
                    "name": "Расстояния",
                    "order": 100,
                    "type": "title"
                },
                "delta_node_and_thin_line": {
                    "value": 100,
                    "name": "Расстояние между вершиной и тонкой линией",
                    "order": 101
                },
                "delta_thins_lines": {
                    "value": 50,
                    "name": "Расстояние между тонкими линиями",
                    "order": 102
                },
                "distance_thin_line_after_connection_x": {
                    "value": 5,
                    "name": "Расстояние тонкой линии после соединения по X",
                    "order": 103
                },
                "distance_thin_line_after_connection_y": {
                    "value": 5,
                    "name": "Расстояние тонкой линии после соединения по Y",
                    "order": 104
                },
                "Стрелки": {
                    "value": "",
                    "name": "Стрелки",
                    "order": 200,
                    "type": "title"
                },
                "arrow_width": {
                    "value": 20,
                    "name": "Ширина стрелки",
                    "order": 201
                },
                "arrow_height": {
                    "value": 8,
                    "name": "Высота стрелки",
                    "order": 202
                },
                "wrap_arrow_length": {
                    "value": 50,
                    "name": "Длина линии стрелки переноса",
                    "order": 203
                }
            }
        },
        "50": {
            "order": 1,
            "type_id": "50",
            "name": "Схема размещения строительных длин и смонтированных муфт на участках регенерации между оконечными пунктами ВОЛП",
            "id_nodes": [
                "50",
                "51"
            ],
            "id_connections": [
                "50"
            ],
            "parameters": {
                "start_x": {
                    "value": 200,
                    "name": "Стартовая координата X",
                    "order": 1
                },
                "start_y": {
                    "value": 200,
                    "name": "Стартовая координата Y",
                    "order": 2
                },
                "delta_wrap_y": {
                    "value": 300,
                    "name": "Расстояние между рядами вершин по Y",
                    "order": 3
                },
                "font_name": {
                    "value": "",
                    "name": "Название шрифта диграммы",
                    "order": 4,
                    "type": "font_name"
                },
                "Тонкие линии": {
                    "value": "",
                    "name": "Тонкие линии",
                    "order": 150,
                    "type": "title"
                },
                "thin_line_color": {
                    "value": "#000000",
                    "name": "Цвет тонкой линии",
                    "order": 151,
                    "type": "color"
                },
                "thin_line_weight": {
                    "value": 2,
                    "name": "Толщина тонкой линии",
                    "order": 152
                },
                "Стрелки": {
                    "value": "",
                    "name": "Стрелки",
                    "order": 200,
                    "type": "title"
                },
                "arrow_width": {
                    "value": 20,
                    "name": "Ширина стрелки",
                    "order": 201
                },
                "arrow_height": {
                    "value": 8,
                    "name": "Высота стрелки",
                    "order": 202
                },
                "wrap_arrow_length": {
                    "value": 50,
                    "name": "Длина линии стрелки переноса",
                    "order": 203
                }
            }
        },
        "100": {
            "order": 2,
            "type_id": "100",
            "name": "Скелетная схема размещения строительных длин кабеля и смонтированных муфт на участке регенерации",
            "id_nodes": ["100", "101", "102"],
            "id_connections": ["100"],
            "parameters": {
                "start_x": {
                    "value": 200,
                    "name": "Стартовая координата X",
                    "order": 1
                },
                "start_y": {
                    "value": 200,
                    "name": "Стартовая координата Y",
                    "order": 2
                },
                "delta_wrap_y": {
                    "value": 300,
                    "name": "Расстояние между рядами вершин по Y",
                    "order": 3
                },
                "font_name": {
                    "value": "",
                    "name": "Название шрифта диграммы",
                    "order": 4,
                    "type": "font_name"
                },
                "Тонкие линии": {
                    "value": "",
                    "name": "Тонкие линии",
                    "order": 150,
                    "type": "title"
                },
                "thin_line_color": {
                    "value": "#000000",
                    "name": "Цвет тонкой линии",
                    "order": 151,
                    "type": "color"
                },
                "thin_line_weight": {
                    "value": 2,
                    "name": "Толщина тонкой линии",
                    "order": 152
                },
                "Стрелки": {
                    "value": "",
                    "name": "Стрелки",
                    "order": 200,
                    "type": "title"
                },
                "arrow_width": {
                    "value": 20,
                    "name": "Ширина стрелки",
                    "order": 201
                },
                "arrow_height": {
                    "value": 8,
                    "name": "Высота стрелки",
                    "order": 202
                },
                "wrap_arrow_length": {
                    "value": 50,
                    "name": "Длина линии стрелки переноса",
                    "order": 203
                }
            }
        },
        "150": {
            "order": 3,
            "type_id": "150",
            "name": "Монтажная схема участка регенерации",
            "id_nodes": [],
            "id_connections": [],
            "parameters": {}
        }
    }
}